import_or_pip
