Metadata-Version: 1.1
Name: import-or-pip
Version: 0.1.2
Summary: import a module or pip install it if it isn't found
Home-page: https://github.com/ubershmekel/import_or_pip
Author: Yuval Greenfield
Author-email: ubershmekel@gmail.com
License: Public Domain
Keywords: import,pip,download
Platform: UNKNOWN
Classifier: Development Status :: 4 - Beta
Classifier: Environment :: Console
Classifier: Intended Audience :: Developers
Classifier: Operating System :: OS Independent
Classifier: Programming Language :: Python :: 2
Classifier: Programming Language :: Python :: 3
Classifier: Topic :: Utilities
Classifier: Topic :: Software Development :: Libraries :: Python Modules
Classifier: Topic :: Software Development :: Build Tools
Classifier: Topic :: Terminals
